snappi_cyperf/RESTasV3.py
snappi_cyperf/Test_l47.py
snappi_cyperf/__init__.py
snappi_cyperf/common.py
snappi_cyperf/cyperfapi.py
snappi_cyperf/exceptions.py
snappi_cyperf/hero.py
snappi_cyperf/hero_1.py
snappi_cyperf/hero_2.py
snappi_cyperf/http_config.py
snappi_cyperf/interface.py
snappi_cyperf/ixrestutils.py
snappi_cyperf/l47server.py
snappi_cyperf/logger.py
snappi_cyperf/objectiveandtimeline.py
snappi_cyperf/ports.py
snappi_cyperf/tcp.py
snappi_cyperf/timer.py
snappi_cyperf-0.0.4.dist-info/METADATA
snappi_cyperf-0.0.4.dist-info/WHEEL
snappi_cyperf-0.0.4.dist-info/top_level.txt
snappi_cyperf-0.0.4.dist-info/RECORD
