Metadata-Version: 2.1
Name: snappi_cyperf
Version: 0.0.4
Summary: The Snappi Cyperf Open Traffic Generator Python Package
Home-page: https://github.com/open-traffic-generator/snappi-cyperf
Author: dipendughosh
Author-email: dipendu.ghosh@keysight.com
License: MIT
Keywords: snappi cyperf testing open traffic generator automation
Classifier: Development Status :: 3 - Alpha
Classifier: Intended Audience :: Developers
Classifier: Topic :: Software Development :: Testing :: Traffic Generation
Classifier: License :: OSI Approved :: MIT License
Classifier: Programming Language :: Python :: 2.7
Classifier: Programming Language :: Python :: 3
Requires-Python: >=2.7, <4
Requires-Dist: requests
Provides-Extra: testing
Requires-Dist: pytest ; extra == 'testing'
Requires-Dist: mock ; extra == 'testing'
Requires-Dist: dpkt ==1.9.4 ; extra == 'testing'
